exrt/__main__.py
exrt/infidelity.py
exrt/metadata.py
exrt/sensitivity.py
exrt-0.1.0.dist-info/METADATA
exrt-0.1.0.dist-info/WHEEL
exrt-0.1.0.dist-info/entry_points.txt
exrt-0.1.0.dist-info/top_level.txt
exrt-0.1.0.dist-info/RECORD
