Metadata-Version: 2.1
Name: exrt
Version: 0.1.0
Summary: Measure robustness of machine learning explanations
Home-page: https://github.com/pidg3/hw-dissertation
Author: Michael Pidgeon
License: GPL
Platform: UNKNOWN
Classifier: Programming Language :: Python :: 3
Classifier: Programming Language :: Python :: 3.8
Requires-Dist: numpy
